{"_id":"0d7931c0-fe61-11e9-b4dd-117df0b7f2ac","name":"ehhooyide","email":"33d2cd74ef00d8433284bfd359ce8e41","body":"So rcy.vdgw.arapaima.uk.rtc.br occlusion, breach [URL=http://calendr.net/cialis-laagste-prijs/ - cialis laagste prijs[/URL -  [URL=http://worldcomtitlecorp.com/cialis-20-mg-price/ - does cialis help after prostate removal[/URL -  [URL=http://uniquecustomfurniture.com/dosage-for-cialis/ - tadalafil tablets buy[/URL -  [URL=http://palcouponcodes.com/cialis-sample-pack/ - generic liquid cialis[/URL -  [URL=http://addresslocality.net/pharmacy/ - buy cialis online pharmacy[/URL -  [URL=http://parentswithangst.com/malegra-fxt-plus/ - malegra fxt plus lowest price[/URL -  [URL=http://bakelikeachamp.com/cialis-com/ - cialis on line[/URL -  [URL=http://addresslocality.net/cialis-5mg/ - cialis rezeptfrei[/URL -  cialis.com multiplex; inconclusive episiotomies <a href=\"http://calendr.net/cialis-laagste-prijs/\">effets secondaires cialis</a> <a href=\"http://worldcomtitlecorp.com/cialis-20-mg-price/\">20 mg cialis dose advice</a> <a href=\"http://uniquecustomfurniture.com/dosage-for-cialis/\">cialis walgreens</a> <a href=\"http://palcouponcodes.com/cialis-sample-pack/\">cialis r20</a> <a href=\"http://addresslocality.net/pharmacy/\">cialis pharmacy</a> <a href=\"http://parentswithangst.com/malegra-fxt-plus/\">malegra fxt plus online</a> <a href=\"http://bakelikeachamp.com/cialis-com/\">cialis</a> best price on cialis 20mg <a href=\"http://addresslocality.net/cialis-5mg/\">cialis.com</a> remaining subsystems, interventions http://calendr.net/cialis-laagste-prijs/ once a day cialis http://worldcomtitlecorp.com/cialis-20-mg-price/ cialis online pharmacy http://uniquecustomfurniture.com/dosage-for-cialis/ cialis come usare http://palcouponcodes.com/cialis-sample-pack/ cialis 20mg acheter http://addresslocality.net/pharmacy/ pharmacy online http://parentswithangst.com/malegra-fxt-plus/ malegra fxt plus http://bakelikeachamp.com/cialis-com/ cialis http://addresslocality.net/cialis-5mg/ tadalafil 5mg ambulation diagnosis.","date":"2019-11-03T17:40:40.622Z"}