{"_id":"361a9430-ff32-11e9-b6d0-c50d5971b899","name":"ydiyokwemeag","email":"9f24f7e2cd64a826d3e6166c300af7c7","body":"Provides zii.phdo.arapaima.uk.oud.rh whey:casein incontinence focally, [URL=http://palcouponcodes.com/cialis-generico-sildenafil/ - cialis generico sildenafil[/URL -  cialis generico sildenafil [URL=http://sammycommunitytransport.org/actor-cialis-commercial/ - cialis mechanism soluderme[/URL -  [URL=http://berksce.com/100-mg-viagra-lowest-price/ - 100 mg viagra lowest price[/URL -  [URL=http://christmastreesnearme.net/cialis-pricing/ - duracion del efecto de cialis[/URL -  [URL=http://leemyles-boulder.com/amoxicillin/ - amoxicillin 500mg capsules[/URL -  [URL=http://nothingbuthoops.net/generic-viagra/ - viagra in canada[/URL -  recovery, <a href=\"http://palcouponcodes.com/cialis-generico-sildenafil/\">cialis info</a> <a href=\"http://sammycommunitytransport.org/actor-cialis-commercial/\">cheap cialis eczederm</a> <a href=\"http://berksce.com/100-mg-viagra-lowest-price/\">viagra</a> <a href=\"http://christmastreesnearme.net/cialis-pricing/\">money online order save cialis</a> <a href=\"http://leemyles-boulder.com/amoxicillin/\">amoxicillin 500mg capsules</a> <a href=\"http://nothingbuthoops.net/generic-viagra/\">generic viagra</a> nausea excuse young http://palcouponcodes.com/cialis-generico-sildenafil/ cialis generico sildenafil http://sammycommunitytransport.org/actor-cialis-commercial/ actor cialis commercial http://berksce.com/100-mg-viagra-lowest-price/ cialis vs viagra http://christmastreesnearme.net/cialis-pricing/ viagra levitra cialis dosage cialis black vs cialis http://leemyles-boulder.com/amoxicillin/ purchase amoxicillin without a prescription http://nothingbuthoops.net/generic-viagra/ viagra for sale circle, inplantation.","date":"2019-11-04T18:37:53.534Z"}