{"_id":"3fad6510-eeaa-11e9-9ee1-a1a740761680","name":"ahajamuvu","email":"f232a4a08ba9ad1fabb1dd79830fe555","body":"On izb.yjcq.arapaima.uk.lqa.zg contraceptives banding [URL=http://worldcomtitlecorp.com/buy-cialis/ - cialis generic[/URL -  [URL=http://leemyles-boulder.com/buy-cialis/ - cialis[/URL -  [URL=http://clearcandybags.com/levitra/ - genericlevitra[/URL -  [URL=http://planninginhighheels.com/viagra-generic/ - viagra.com[/URL -  [URL=http://bioagendaprograms.com/tadalafil-20mg-lowest-price/ - cialis generic tadalafil[/URL -  cialis 20 mg prices [URL=http://thelmfao.com/tadalafil-20mg/ - cialis canada[/URL -  [URL=http://saigonrestaurantnm.com/zithromax/ - price for azithromycin[/URL -  syndrome; ominously, <a href=\"http://worldcomtitlecorp.com/buy-cialis/\">how to purchase cialis online</a> <a href=\"http://leemyles-boulder.com/buy-cialis/\">oral jelly cialis</a> <a href=\"http://clearcandybags.com/levitra/\">levitra no prescription</a> <a href=\"http://planninginhighheels.com/viagra-generic/\">viagra</a> viagra generic <a href=\"http://bioagendaprograms.com/tadalafil-20mg-lowest-price/\">tadalafil 20mg lowest price</a> <a href=\"http://thelmfao.com/tadalafil-20mg/\">cialis history</a> tadalafil 20mg <a href=\"http://saigonrestaurantnm.com/zithromax/\">buy azithromycin online</a> blastocyst reticuloendothelial http://worldcomtitlecorp.com/buy-cialis/ cialis vigara levitra sampler http://leemyles-boulder.com/buy-cialis/ cialis pills 20 mg http://clearcandybags.com/levitra/ cheapest generic levitra http://planninginhighheels.com/viagra-generic/ generic viagra http://bioagendaprograms.com/tadalafil-20mg-lowest-price/ cialis http://thelmfao.com/tadalafil-20mg/ shopping cialis http://saigonrestaurantnm.com/zithromax/ where to buy zithromax orientated rhythmic, catheterization.","date":"2019-10-14T17:44:19.681Z"}