{"_id":"40d970e0-e505-11e9-aaf3-f967e61813d6","name":"agisuulu","email":"c90168a565679342fbc1adbca491d604","body":"Reducing got.qxvs.arapaima.uk.wnr.eq retake [URL=http://aawaaart.com/viagra-online/ - viagra pictures[/URL -  [URL=http://nitdb.org/cialis-with-dapoxetine/ - cialis with dapoxetine canada[/URL -  [URL=http://americanartgalleryandgifts.com/lotensin/ - buy lotensin[/URL -  [URL=http://nothingbuthoops.net/super-kamagra/ - super kamagra[/URL -  [URL=http://best-online-mba.net/gyne-lotrimin/ - gyne-lotrimin pills[/URL -  [URL=http://fbwhatsapquotes.com/kamagra-jelly/ - viagra paten[/URL -  [URL=http://planninginhighheels.com/cheap-viagra/ - buy viagra cheap[/URL -  [URL=http://cbfsupply.com/rizact/ - discount rizact[/URL -  scraped beginning <a href=\"http://aawaaart.com/viagra-online/\">online viagra</a> <a href=\"http://nitdb.org/cialis-with-dapoxetine/\">discount cialis with dapoxetine</a> <a href=\"http://americanartgalleryandgifts.com/lotensin/\">lotensin online</a> <a href=\"http://nothingbuthoops.net/super-kamagra/\">super kamagra</a> <a href=\"http://best-online-mba.net/gyne-lotrimin/\">cheap gyne-lotrimin</a> <a href=\"http://fbwhatsapquotes.com/kamagra-jelly/\">buy kamagra</a> <a href=\"http://planninginhighheels.com/cheap-viagra/\">viagra</a> <a href=\"http://cbfsupply.com/rizact/\">buy rizact</a> hydroceles requirements thick http://aawaaart.com/viagra-online/ viagra alternatives http://nitdb.org/cialis-with-dapoxetine/ cialis with dapoxetine http://americanartgalleryandgifts.com/lotensin/ lotensin online http://nothingbuthoops.net/super-kamagra/ super kamagra http://best-online-mba.net/gyne-lotrimin/ gyne-lotrimin online http://fbwhatsapquotes.com/kamagra-jelly/ buy viagra in lagos nigeria 12 http://planninginhighheels.com/cheap-viagra/ cheap viagra http://cbfsupply.com/rizact/ buy rizact online glass ensure, possible.","date":"2019-10-02T11:10:34.001Z"}