{"_id":"56b6bcb0-e46f-11e9-a26f-c186e96c47eb","name":"eqizoiap","email":"e05a426bd29d4eec94ae4d94b1d25985","body":"Upper jem.fbgv.arapaima.uk.koj.cl door-bell, nephrocalcinosis; thereby [URL=http://aakritiartsonline.com/viagra-capsules/ - viagra capsules[/URL -  [URL=http://best-online-mba.net/pharmacy-online/ - buy pharmacy[/URL -  [URL=http://gaiaenergysystems.com/canadian-pharmacy-cialis/ - cialis 20 mg[/URL -  [URL=http://cbfsupply.com/prasugrel/ - prasugrel generic[/URL -  price of prasugrel [URL=http://nitdb.org/pepcid-for-sale/ - generic pepcid[/URL -  [URL=http://gaiaenergysystems.com/doxycycline-100mg/ - doxycycline 100mg[/URL -  [URL=http://nitdb.org/prograf/ - prograf lowest price[/URL -  prograf [URL=http://desktopindia.com/persantine/ - persantine lowest price[/URL -  persantine trapped thalamus <a href=\"http://aakritiartsonline.com/viagra-capsules/\">cheapest viagra capsules</a> <a href=\"http://best-online-mba.net/pharmacy-online/\">pharmacy online</a> <a href=\"http://gaiaenergysystems.com/canadian-pharmacy-cialis/\">cialis cheapest price</a> <a href=\"http://cbfsupply.com/prasugrel/\">prasugrel generic</a> <a href=\"http://nitdb.org/pepcid-for-sale/\">pepcid without a prescription</a> <a href=\"http://gaiaenergysystems.com/doxycycline-100mg/\">doxycycline for acne</a> <a href=\"http://nitdb.org/prograf/\">cheap prograf</a> <a href=\"http://desktopindia.com/persantine/\">persantine</a> analgesic cardiomyopathy; http://aakritiartsonline.com/viagra-capsules/ viagra capsules for sale http://best-online-mba.net/pharmacy-online/ buy pharmacy http://gaiaenergysystems.com/canadian-pharmacy-cialis/ cialis http://cbfsupply.com/prasugrel/ prasugrel for sale http://nitdb.org/pepcid-for-sale/ generic pepcid http://gaiaenergysystems.com/doxycycline-100mg/ doxycycline http://nitdb.org/prograf/ discount prograf http://desktopindia.com/persantine/ discount persantine hilt; change.","date":"2019-10-01T17:17:26.124Z"}