{"_id":"660049e0-48ef-11ea-aabc-91fe5beb9ae2","name":"Alanfelve","email":"4c6c8765aec5e5ac639254aa889fb7f2","body":"<a href=\"http://zoloft365.com/\">600mg zoloft</a> <a href=\"http://hydrochlorothiazidemed.com/\">hydrochlorothiazide 12.5 mg</a> <a href=\"http://albuterol360.com/\">albuterol tablets over the counter</a> <a href=\"http://vardenafilev.com/\">vardenafil 20</a> <a href=\"http://atarax2020.com/\">atarax 10mg</a> <a href=\"http://amoxiciline.com/\">amoxicillin 500 mg price</a>","date":"2020-02-06T14:46:03.649Z"}