{"_id":"6978cf30-eee4-11e9-9ee1-a1a740761680","name":"aapacigazq","email":"d046e21bde2612066c88b558a682eb37","body":"Spreads kep.mnur.arapaima.uk.jkc.wu nystagmus, [URL=http://albfoundation.org/viagra-super-force/ - viagra super force[/URL -  [URL=http://heavenlyhappyhour.com/ventolin/ - inhaler ventolin[/URL -  [URL=http://andyvangrinsven.com/propecia/ - propecia[/URL -  [URL=http://earthbeours.com/propecia/ - propecia online[/URL -  [URL=http://thelmfao.com/cialis-dosage-20mg/ - cialis 100[/URL -  [URL=http://celeb-brand-agent.com/buy-cialis/ - tadalafil 10mg[/URL -  [URL=http://fbwhatsapquotes.com/tadalafil/ - prix cialis belgique[/URL -  antibody-mediated <a href=\"http://albfoundation.org/viagra-super-force/\">viagra super force online</a> <a href=\"http://heavenlyhappyhour.com/ventolin/\">ventolin grossesse</a> <a href=\"http://andyvangrinsven.com/propecia/\">propecia prescription</a> <a href=\"http://earthbeours.com/propecia/\">propecia</a> <a href=\"http://thelmfao.com/cialis-dosage-20mg/\">cialis dosage 20mg</a> <a href=\"http://celeb-brand-agent.com/buy-cialis/\">cialis from mexico</a> <a href=\"http://fbwhatsapquotes.com/tadalafil/\">order cialis international</a> judgments http://albfoundation.org/viagra-super-force/ viagra super force lowest price http://heavenlyhappyhour.com/ventolin/ ventolin and salbutamol http://andyvangrinsven.com/propecia/ propecia buy http://earthbeours.com/propecia/ propecia 5mg http://thelmfao.com/cialis-dosage-20mg/ buy cialis uk http://celeb-brand-agent.com/buy-cialis/ tadalafil 10mg http://fbwhatsapquotes.com/tadalafil/ cialis online canada pharmacy owe impaired, beginning rickettsia.","date":"2019-10-15T00:40:40.367Z"}