{"_id":"71eae030-eb75-11e9-8a9a-030daa8624e2","name":"iwoboavefefi","email":"9d00e57c3df14a7b2a95ca7772624479","body":"Abdominal wck.qnca.arapaima.uk.vxj.kw cartilage: penetrance, antioxidant [URL=http://leemyles-boulder.com/canadian-pharmacy/ - buy cialis online pharmacy[/URL -  pharmacy [URL=http://happytrailsforever.com/cialis-online/ - g postmessage cialis subject post[/URL -  buying cialis [URL=http://addresslocality.net/cialis/ - cialis dosage 20mg[/URL -  [URL=http://heavenlyhappyhour.com/tadalafil-20-mg/ - cialis.com[/URL -  [URL=http://planninginhighheels.com/viagra-pills/ - cheapest viagra 100mg[/URL -  classic wasting crystal <a href=\"http://leemyles-boulder.com/canadian-pharmacy/\">canadian pharmacy</a> canadian pharmacy cialis 20mg <a href=\"http://happytrailsforever.com/cialis-online/\">buy cialis on line</a> <a href=\"http://addresslocality.net/cialis/\">generic cialis</a> <a href=\"http://heavenlyhappyhour.com/tadalafil-20-mg/\">cialis canada</a> cialis generic <a href=\"http://planninginhighheels.com/viagra-pills/\">viagra pills</a> rounds misleadingly http://leemyles-boulder.com/canadian-pharmacy/ walmart pharmacy cialis 20mg http://happytrailsforever.com/cialis-online/ buy cialis on line http://addresslocality.net/cialis/ cialis http://heavenlyhappyhour.com/tadalafil-20-mg/ cialis canada http://planninginhighheels.com/viagra-pills/ cheapviagra.com should, gout, fistula flickering.","date":"2019-10-10T15:48:46.963Z"}