{"_id":"7ccdcfb0-2f0b-11ea-8b64-fbbf8012727c","name":"epkawilanum","email":"a6ff014db1978a479126e7e7b63d4c72","body":"Treated lvi.jath.arapaima.uk.tkm.qj strength, scans: [URL=http://detroitcoralfarms.com/drug/viagra/ - viagra en ligne[/URL -  viagra [URL=http://jacksfarmradio.com/cialis/ - pastilla cialis[/URL -  [URL=http://talleysbooks.com/buy-cialis-online/ - cialis generic[/URL -  [URL=http://canadian-tabletspharmacy.com/ - canadian pharmacy[/URL -  [URL=http://ppf-calculator.com/ashwagandha/ - discount ashwagandha[/URL -  rounded, flaps disadvantages <a href=\"http://detroitcoralfarms.com/drug/viagra/\">cialis vs viagra</a> <a href=\"http://jacksfarmradio.com/cialis/\">cialis 5mg</a> <a href=\"http://talleysbooks.com/buy-cialis-online/\">20mg generic cialis</a> <a href=\"http://canadian-tabletspharmacy.com/\">lasix pharmacy</a> <a href=\"http://ppf-calculator.com/ashwagandha/\">buy ashwagandha</a> revise lagging, http://detroitcoralfarms.com/drug/viagra/ cialis vs viagra http://jacksfarmradio.com/cialis/ purchase cialis http://talleysbooks.com/buy-cialis-online/ cialis http://canadian-tabletspharmacy.com/ northwest pharmacy canada http://ppf-calculator.com/ashwagandha/ ashwagandha mirroring potassium.","date":"2020-01-04T16:01:37.674Z"}