{"_id":"840b7e40-f026-11e9-91d0-b51b18cda47a","name":"ijifojizuja","email":"9566597fa7937c8fb6048b34b6cb5490","body":"The jil.cnfs.arapaima.uk.kpw.lm ? [URL=http://heavenlyhappyhour.com/cialis-com/ - cialis 10 mg[/URL -  [URL=http://thelmfao.com/cialis-without-prescription/ - cialis fast and cheap canada[/URL -  [URL=http://thelmfao.com/cialis-coupon/ - tadalafil 20 mg best price[/URL -  [URL=http://celeb-brand-agent.com/generic-cialis-canada/ - generic tadalafil 5 mg[/URL -  [URL=http://addresslocality.net/priligy/ - priligy online[/URL -  [URL=http://worldcomtitlecorp.com/levitra-20mg/ - levitra coupon[/URL -  [URL=http://cheapflights-advice.org/amoxicillin/ - amoxicillin 500mg capsules[/URL -  [URL=http://happytrailsforever.com/amoxicillin/ - amoxicillin[/URL -  [URL=http://russianpoetsfund.com/lasix/ - furosemide without prescription[/URL -  lasix no prescription carer originally swelling, <a href=\"http://heavenlyhappyhour.com/cialis-com/\">low cost cialis 20mg</a> <a href=\"http://thelmfao.com/cialis-without-prescription/\">buy generic cialis online uk</a> <a href=\"http://thelmfao.com/cialis-coupon/\">cialis coupon 5mg</a> <a href=\"http://celeb-brand-agent.com/generic-cialis-canada/\">generic cialis paypal</a> <a href=\"http://addresslocality.net/priligy/\">dapoxetine 60mg</a> <a href=\"http://worldcomtitlecorp.com/levitra-20mg/\">levitra</a> <a href=\"http://cheapflights-advice.org/amoxicillin/\">amoxicillin for sale</a> <a href=\"http://happytrailsforever.com/amoxicillin/\">amoxicillin without a prescription</a> <a href=\"http://russianpoetsfund.com/lasix/\">lasix on line</a> sculpted http://heavenlyhappyhour.com/cialis-com/ cialis http://thelmfao.com/cialis-without-prescription/ cialis online no presciption http://thelmfao.com/cialis-coupon/ where to get cialis without a precription http://celeb-brand-agent.com/generic-cialis-canada/ guaranteed lowest price on cialis http://addresslocality.net/priligy/ dapoxetine http://worldcomtitlecorp.com/levitra-20mg/ la levitra http://cheapflights-advice.org/amoxicillin/ buy amoxicillin online amoxicillin http://happytrailsforever.com/amoxicillin/ amoxicillin 500 mg http://russianpoetsfund.com/lasix/ lasix discussing backwards complicated universal.","date":"2019-10-16T15:06:23.180Z"}