{"_id":"84983780-0085-11ea-b249-d7f5a814ea25","name":"anxufwae","email":"b73e70447784af560caf30dfd913728f","body":"K shn.wfbr.arapaima.uk.cyn.am volar menopausal [URL=http://stockprofitpros.com/biociclin-cialis-soft/ - opinioni cialis[/URL -  [URL=http://reubendangoor.com/cialis-heart-disease/ - zapiro cartoon cialis[/URL -  [URL=http://uniquecustomfurniture.com/cialis-yetkili-sat/ - cialis canada online pharmacy[/URL -  cialis online avis search [URL=http://azlyricsall.com/beta-bloccanti-con-cialis/ - cialis savings accounts in south africa[/URL -  [URL=http://palcouponcodes.com/cialis-generico-sildenafil/ - cialis otros nombres[/URL -  [URL=http://sammycommunitytransport.org/cialis-mg-dose/ - cheap cialis without a prescription[/URL -  [URL=http://ekautorepair.com/5mg-cialis-side-effects/ - generic cialis prices[/URL -  how much cialis can i take [URL=http://azlyricsall.com/cialis-mg-per-serving/ - cialis 5 mg receta[/URL -  [URL=http://historicgrandhotels.com/order-cialis/ - viagra cialis canadian pharmacy[/URL -  sublingual retraction <a href=\"http://stockprofitpros.com/biociclin-cialis-soft/\">names for generic cialis</a> <a href=\"http://reubendangoor.com/cialis-heart-disease/\">cialis coupons for pharmacy</a> <a href=\"http://uniquecustomfurniture.com/cialis-yetkili-sat/\">cialis yetkili sat</a> <a href=\"http://azlyricsall.com/beta-bloccanti-con-cialis/\">canadian pharmacy and cialis</a> beta bloccanti con cialis <a href=\"http://palcouponcodes.com/cialis-generico-sildenafil/\">cialis generico sildenafil</a> <a href=\"http://sammycommunitytransport.org/cialis-mg-dose/\">cheap cialis without a prescription</a> cheap cialis without a prescription <a href=\"http://ekautorepair.com/5mg-cialis-side-effects/\">how much cialis can i take</a> <a href=\"http://azlyricsall.com/cialis-mg-per-serving/\">cialis on line canada</a> <a href=\"http://historicgrandhotels.com/order-cialis/\">viagra cialis canadian pharmacy</a> throats laxative http://stockprofitpros.com/biociclin-cialis-soft/ developing medical products cialis http://reubendangoor.com/cialis-heart-disease/ buy discount generic cialis http://uniquecustomfurniture.com/cialis-yetkili-sat/ cialis online avis search http://azlyricsall.com/beta-bloccanti-con-cialis/ beta bloccanti con cialis http://palcouponcodes.com/cialis-generico-sildenafil/ can you order cialis online http://sammycommunitytransport.org/cialis-mg-dose/ chi ha mai provato il cialis http://ekautorepair.com/5mg-cialis-side-effects/ is cialis available in generic http://azlyricsall.com/cialis-mg-per-serving/ cialis 5 mg receta http://historicgrandhotels.com/order-cialis/ cheap cialis paediatric rounded arthrotomy.","date":"2019-11-06T11:06:44.990Z"}