{"_id":"8e7d94b0-3597-11ea-b0ee-739e99126730","name":"imicifif","email":"c42fbf1cd9c085d7a045a9e105f647c7","body":"Treatment: zpx.blio.arapaima.uk.psl.hr deviated, [URL=http://scoutcampreviews.com/super-avana-online/#super-avana - super avana online[/URL -  [URL=http://sobrietycelebrations.com/tim-b/#discount-cialis - cialis from canada[/URL -  [URL=http://nitdb.org/cheap-viagra/#cheap-viagra - cialis vs viagra[/URL -  [URL=http://ekautorepair.com/cialis-bran/#cialis-and-niacin - cialis bran[/URL -  cialis generika [URL=http://alanhawkshaw.net/40/#online-propecia-prescription - cheap propecia online[/URL -  [URL=http://scoverage.org/amoxicillin-500-mg/#buy-amoxicillin-online - buy amoxicillin online[/URL -  [URL=http://palawan-resorts.com/discount-viagra/#generic-viagra-100mg-price - canada viagra[/URL -  [URL=http://lovecamels.com/drug/prednisone/#prednisone-10-mg - prednisone 10 mg[/URL -  cat <a href=\"http://scoutcampreviews.com/super-avana-online/#super-avana-lowest-price\">buy super avana online</a> cheap super avana <a href=\"http://sobrietycelebrations.com/tim-b/#cialis-5-mg\">cialis 5 mg</a> <a href=\"http://nitdb.org/cheap-viagra/#cheap-viagra\">price of viagra</a> <a href=\"http://ekautorepair.com/cialis-bran/#cialis-bran\">viagra cialis compare cpx24</a> <a href=\"http://alanhawkshaw.net/40/#propecia-5mg\">propecia buy</a> <a href=\"http://scoverage.org/amoxicillin-500-mg/#amoxicillin\">amoxicillin</a> amoxicillin <a href=\"http://palawan-resorts.com/discount-viagra/#discount-viagra\">buy viagra online uk</a> <a href=\"http://lovecamels.com/drug/prednisone/#by-prednisone-w-not-prescription\">prednisone</a> deter positioned http://scoutcampreviews.com/super-avana-online/#discount-super-avana super avana online http://sobrietycelebrations.com/tim-b/#cialis-from-canada cialis 20 mg lowest price http://nitdb.org/cheap-viagra/#cheap-viagra cheap viagra cheap viagra http://ekautorepair.com/cialis-bran/#cialis-tablets-for-sale cialis bran http://alanhawkshaw.net/40/#buy-generic-propecia propecia http://scoverage.org/amoxicillin-500-mg/#buy-amoxicillin-online amoxicillin 500 mg amoxicillin 500 mg http://palawan-resorts.com/discount-viagra/#canada-viagra cheap viagra http://lovecamels.com/drug/prednisone/#prednisone-10-mg prednisone buy acidic gangrene conscious ulceration.","date":"2020-01-12T23:59:23.795Z"}