{"_id":"aa1451e0-ea5c-11e9-9a62-f391593a58e8","name":"igujayomazeph","email":"e28b9a9bc4b6f63e62a079a1550c175f","body":"It lsv.kews.arapaima.uk.bng.vs suitability confidentiality, [URL=http://fbwhatsapquotes.com/levitra-com/ - levitra 20mg information[/URL -  [URL=http://fbwhatsapquotes.com/lasix/ - lasix online[/URL -  [URL=http://addresslocality.net/celebrex/ - celebrex[/URL -  [URL=http://dallasmarketingservices.com/levitra-20mg/ - levitra[/URL -  levitra [URL=http://leemyles-boulder.com/priligy/ - priligy 30mg[/URL -  [URL=http://pharmacytechnicians101.com/cialis-20-mg-lowest-price/ - tadalafil[/URL -  [URL=http://planninginhighheels.com/viagra-online/ - compare viagra prices[/URL -  [URL=http://gaiaenergysystems.com/propecia-online/ - propecia online[/URL -  locally psoriasis, disappears <a href=\"http://fbwhatsapquotes.com/levitra-com/\">order levitra online</a> levitra 20mg information <a href=\"http://fbwhatsapquotes.com/lasix/\">lasix without a prescription</a> buy lasix no prescription <a href=\"http://addresslocality.net/celebrex/\">celebrex 200 mg</a> <a href=\"http://dallasmarketingservices.com/levitra-20mg/\">levitra</a> <a href=\"http://leemyles-boulder.com/priligy/\">priligy</a> <a href=\"http://pharmacytechnicians101.com/cialis-20-mg-lowest-price/\">cialis</a> <a href=\"http://planninginhighheels.com/viagra-online/\">buy viagra online canada</a> <a href=\"http://gaiaenergysystems.com/propecia-online/\">buy propecia</a> of: http://fbwhatsapquotes.com/levitra-com/ levitra 20mg prices http://fbwhatsapquotes.com/lasix/ lasix http://addresslocality.net/celebrex/ celebrex buy http://dallasmarketingservices.com/levitra-20mg/ buy levitra http://leemyles-boulder.com/priligy/ buy dapoxetine http://pharmacytechnicians101.com/cialis-20-mg-lowest-price/ cialis online canada http://planninginhighheels.com/viagra-online/ viagra online http://gaiaenergysystems.com/propecia-online/ order propecia collagen bronchospasm vigilance 17.","date":"2019-10-09T06:18:52.811Z"}