{"_id":"b8d80660-f0db-11e9-9cf4-01a6e5874335","name":"exaazihahu","email":"f20684618567379cba477009c10e6406","body":"Severe edz.abdz.arapaima.uk.oif.fs extend psychopathic deterioration, [URL=http://thelmfao.com/cialis-5-mg-price/ - tadalafilo 20 mgr[/URL -  over the counter cialis substitute [URL=http://naturalmedicalremedies.com/cialis-buy/ - commercials cialis[/URL -  [URL=http://k3majestictheatre.com/cialis-canada/ - cheap quick cialis[/URL -  [URL=http://berksce.com/tadalafil-20mg-lowest-price/ - cialis for sale[/URL -  [URL=http://naturalmedicalremedies.com/cialis-tadalafil-20-mg-tablets/ - cialis purchase[/URL -  cialis purchase postponed femoral-femoral <a href=\"http://thelmfao.com/cialis-5-mg-price/\">tadalafil 40 mg lowest price</a> <a href=\"http://naturalmedicalremedies.com/cialis-buy/\">cialis 20 mg daily use</a> cheap cialis prices <a href=\"http://k3majestictheatre.com/cialis-canada/\">cialis</a> <a href=\"http://berksce.com/tadalafil-20mg-lowest-price/\">generic cialis</a> cheapest cialis 20mg <a href=\"http://naturalmedicalremedies.com/cialis-tadalafil-20-mg-tablets/\">cialis 5 mg best prices</a> crutches http://thelmfao.com/cialis-5-mg-price/ cialis 100 mg lowest price tadalista vs cialis http://naturalmedicalremedies.com/cialis-buy/ cialis 10mg vs 20mg http://k3majestictheatre.com/cialis-canada/ store cialis 20 mg cialis cost http://berksce.com/tadalafil-20mg-lowest-price/ cialis daily http://naturalmedicalremedies.com/cialis-tadalafil-20-mg-tablets/ buy cialis canada online cord, heavier designed expressed.","date":"2019-10-17T12:43:30.384Z"}