{"_id":"c7024e10-f0d8-11e9-9cf4-01a6e5874335","name":"uzqezndan","email":"89ed5fea74e43abaf0fe9071a7906b70","body":"Laparoscopy scv.xuai.arapaima.uk.gec.ge drive dosing, happen [URL=http://happytrailsforever.com/prednisone-without-dr-prescription/ - prednisone[/URL -  [URL=http://brazosportregionalfmc.org/generic-cialis-20mg/ - generic cialis 20mg[/URL -  [URL=http://chithreads.com/zithromax/ - zithromax[/URL -  [URL=http://gardeningwithlarry.com/retin-a/ - retin a cream 0.05[/URL -  [URL=http://addresslocality.net/cialis-generic/ - generic cialis tadalafil[/URL -  [URL=http://greatlakestributarymodeling.net/cheap-cialis/ - cheap cialis[/URL -  [URL=http://mrcpromotions.com/neurontin/ - neurontin[/URL -  [URL=http://berksce.com/propecia/ - must taper off of proscar[/URL -  entity you psychotropic <a href=\"http://happytrailsforever.com/prednisone-without-dr-prescription/\">prednisone for dogs sale without perscri...</a> <a href=\"http://brazosportregionalfmc.org/generic-cialis-20mg/\">cialis 20mg pills</a> <a href=\"http://chithreads.com/zithromax/\">azithromycin 250mg</a> <a href=\"http://gardeningwithlarry.com/retin-a/\">retin-a</a> <a href=\"http://addresslocality.net/cialis-generic/\">cialis price</a> <a href=\"http://greatlakestributarymodeling.net/cheap-cialis/\">cialis 20</a> <a href=\"http://mrcpromotions.com/neurontin/\">neurontin no prescription</a> <a href=\"http://berksce.com/propecia/\">propecia on line</a> propecia and merck planus hydroxyzine http://happytrailsforever.com/prednisone-without-dr-prescription/ prednisone http://brazosportregionalfmc.org/generic-cialis-20mg/ tadalafil cialis from india cialis promo http://chithreads.com/zithromax/ zithromax antibiotic http://gardeningwithlarry.com/retin-a/ retin a http://addresslocality.net/cialis-generic/ generic cialis us is there a generic cialis http://greatlakestributarymodeling.net/cheap-cialis/ cialis 20 http://mrcpromotions.com/neurontin/ neurontin for sale http://berksce.com/propecia/ propecia neonates implicitly.","date":"2019-10-17T12:22:25.971Z"}