{"_id":"c70f04a0-ebbc-11e9-8a9a-030daa8624e2","name":"umudzodivicu","email":"ff183e08de7466245ab7ef7e654e8447","body":"Rinse xbn.nrrg.arapaima.uk.bfk.ww oratory, [URL=http://chithreads.com/propecia/ - order propecia[/URL -  [URL=http://fbwhatsapquotes.com/generic-levitra/ - levitra[/URL -  [URL=http://thelmfao.com/generic-cialis-from-canada/ - tadalafil 5 mg best price usa[/URL -  [URL=http://theswordguy.com/lioresal/ - buy lioresal[/URL -  [URL=http://disclosenews.com/vibramycin/ - vibramycin[/URL -  [URL=http://andyvangrinsven.com/lasix/ - lasix[/URL -  [URL=http://pinecreektheatre.org/accutane/ - buy generic accutane[/URL -  [URL=http://anguillacayseniorliving.com/buy-accutane-online/ - accutane buy[/URL -  castrus props wake <a href=\"http://chithreads.com/propecia/\">propecia</a> <a href=\"http://fbwhatsapquotes.com/generic-levitra/\">levitra 20mg</a> <a href=\"http://thelmfao.com/generic-cialis-from-canada/\">generic cialis from canada</a> <a href=\"http://theswordguy.com/lioresal/\">lioresal online</a> baclofen without a prescription <a href=\"http://disclosenews.com/vibramycin/\">generic vibramycin</a> <a href=\"http://andyvangrinsven.com/lasix/\">lasix without a prescription</a> <a href=\"http://pinecreektheatre.org/accutane/\">order accutaneonline</a> <a href=\"http://anguillacayseniorliving.com/buy-accutane-online/\">where can i buy accutane online</a> regularly eyebrow http://chithreads.com/propecia/ buy propecia online http://fbwhatsapquotes.com/generic-levitra/ generic levitra http://thelmfao.com/generic-cialis-from-canada/ best prices on cialis 10mg http://theswordguy.com/lioresal/ lioresal http://disclosenews.com/vibramycin/ cheapest vibramycin http://andyvangrinsven.com/lasix/ lasix without prescription http://pinecreektheatre.org/accutane/ accutane order online accutane to buy http://anguillacayseniorliving.com/buy-accutane-online/ buy accutane online aiming book.","date":"2019-10-11T00:19:24.024Z"}