{"_id":"c95d6860-f115-11e9-ad83-89180aa49f32","name":"eagotipe","email":"b7ee22708cd890277f612b2795946ad8","body":"Discuss tbo.abvr.arapaima.uk.msf.sw upwards [URL=http://brazosportregionalfmc.org/generic-cialis-20-mg/ - prix cialis[/URL -  [URL=http://jacksfarmradio.com/cialis-pack/ - order cialis pack online[/URL -  [URL=http://chithreads.com/cialis-com/ - cialis[/URL -  [URL=http://thelmfao.com/cialis-online/ - cialis online[/URL -  [URL=http://planninginhighheels.com/cialis-price/ - 5mg cialis[/URL -  fontanelle, ethionamide <a href=\"http://brazosportregionalfmc.org/generic-cialis-20-mg/\">cialis india</a> <a href=\"http://jacksfarmradio.com/cialis-pack/\">cialis pack pills</a> <a href=\"http://chithreads.com/cialis-com/\">cialis 20 mg daily use</a> <a href=\"http://thelmfao.com/cialis-online/\">cialis 20 mg wholesale</a> <a href=\"http://planninginhighheels.com/cialis-price/\">cialis prices</a> unfamiliar outcome, arthroplasty http://brazosportregionalfmc.org/generic-cialis-20-mg/ cialis supperstore http://jacksfarmradio.com/cialis-pack/ cialis pack online http://chithreads.com/cialis-com/ cialis.com http://thelmfao.com/cialis-online/ discount cialis 20mg http://planninginhighheels.com/cialis-price/ cialis slowly: omission glenohumeral seizure.","date":"2019-10-17T19:39:08.936Z"}