{"_id":"e1a66be0-f3d3-11e9-9fd2-b7b38e4fb89c","name":"obuleyotax","email":"eb393cec9e2d039aed4a126bba6b45c5","body":"This nkw.xaay.arapaima.uk.mli.lz hunt [URL=http://gaiaenergysystems.com/amoxicillin-500mg-capsules/ - amoxicillin 500mg[/URL -  amoxicillin 500mg [URL=http://bigskilletlive.com/cialis-20-mg-price/ - cialis generic canada[/URL -  [URL=http://dallasmarketingservices.com/viagra/ - buying viagra[/URL -  discount viagra [URL=http://heavenlyhappyhour.com/cialis-generic/ - cialis 5 mg coupon[/URL -  [URL=http://k3majestictheatre.com/buy-cialis-online/ - buy cialis online[/URL -  [URL=http://leemyles-boulder.com/buy-levitra-online/ - discount levitra[/URL -  generic levitra 20mg [URL=http://heavenlyhappyhour.com/propecia/ - buy propecia online[/URL -  audit insufficiently <a href=\"http://gaiaenergysystems.com/amoxicillin-500mg-capsules/\">amoxicillin</a> <a href=\"http://bigskilletlive.com/cialis-20-mg-price/\">tadalafil 5mg</a> <a href=\"http://dallasmarketingservices.com/viagra/\">buying viagra</a> <a href=\"http://heavenlyhappyhour.com/cialis-generic/\">cialis generic 20 mg</a> lowest price cialis <a href=\"http://k3majestictheatre.com/buy-cialis-online/\">tadalafil generic cialis 20 mg</a> <a href=\"http://leemyles-boulder.com/buy-levitra-online/\">vardenafil 20 mg</a> <a href=\"http://heavenlyhappyhour.com/propecia/\">order propecia</a> for, shelf travels http://gaiaenergysystems.com/amoxicillin-500mg-capsules/ amoxicillin http://bigskilletlive.com/cialis-20-mg-price/ cialis 20 mg price http://dallasmarketingservices.com/viagra/ buying viagra http://heavenlyhappyhour.com/cialis-generic/ cialis generic 20 mg http://k3majestictheatre.com/buy-cialis-online/ generic daily cialis http://leemyles-boulder.com/buy-levitra-online/ levitra 20 mg http://heavenlyhappyhour.com/propecia/ propecia for sale fibrosis, team?","date":"2019-10-21T07:24:56.361Z"}