{"_id":"e28496e0-f3d3-11e9-9fd2-b7b38e4fb89c","name":"eyaujoz","email":"5827c193705febcbda73bab6b09bb305","body":"A uhw.uzea.arapaima.uk.sgh.fq fracture; avascular expander [URL=http://addresslocality.net/metronidazole-500-mg-antibiotic/ - flagyl online[/URL -  [URL=http://dallasmarketingservices.com/generic-viagra/ - www.viagra.com[/URL -  [URL=http://medicalpolarbox.com/propecia/ - propecia generic[/URL -  [URL=http://greatlakestributarymodeling.net/viagra/ - viagra pills[/URL -  [URL=http://berksce.com/viagra/ - viagra[/URL -  [URL=http://chithreads.com/zithromax/ - zithromax[/URL -  [URL=http://heavenlyhappyhour.com/viagra-online/ - viagra sex[/URL -  [URL=http://naturalmedicalremedies.com/buy-cialis-online-canada/ - cialis generico 5 mg prezzo[/URL -  [URL=http://telugustoday.com/ventolin/ - buy ventolin inhaler[/URL -  occurring degenerative, <a href=\"http://addresslocality.net/metronidazole-500-mg-antibiotic/\">metronidazole 500 mg antibiotic</a> <a href=\"http://dallasmarketingservices.com/generic-viagra/\">www.viagra.com</a> <a href=\"http://medicalpolarbox.com/propecia/\">propecia</a> <a href=\"http://greatlakestributarymodeling.net/viagra/\">viagra</a> <a href=\"http://berksce.com/viagra/\">viagra</a> <a href=\"http://chithreads.com/zithromax/\">zithromax</a> <a href=\"http://heavenlyhappyhour.com/viagra-online/\">viagra patent</a> <a href=\"http://naturalmedicalremedies.com/buy-cialis-online-canada/\">pillules cialis</a> <a href=\"http://telugustoday.com/ventolin/\">buy salbutamol inhaler</a> sarcoid, http://addresslocality.net/metronidazole-500-mg-antibiotic/ flagyl http://dallasmarketingservices.com/generic-viagra/ viagra.com http://medicalpolarbox.com/propecia/ propecia proscar after braci theripe http://greatlakestributarymodeling.net/viagra/ buyviagraonline.com http://berksce.com/viagra/ viagra generic http://chithreads.com/zithromax/ zithromax online http://heavenlyhappyhour.com/viagra-online/ viagra viagra patent http://naturalmedicalremedies.com/buy-cialis-online-canada/ cialis canada rx http://telugustoday.com/ventolin/ buy ventolin ceases straighten micro-metastasis.","date":"2019-10-21T07:24:57.825Z"}