{"_id":"ea38ea50-fe53-11e9-b4dd-117df0b7f2ac","name":"Manuelfrulp","email":"d36ee6d33b1d24a4515933ddfbbc8fa1","body":"Regards. I appreciate it! \r\nhttp://advairmsnrxmsnrx.best/\r\nhttp://cytoteconline.fr/\r\nhttp://dapoxetineonline.fr/\r\nhttp://ventolinrx.fr/\r\nhttp://zovirax.fr/\r\nhttp://bactrim.fr/\r\nhttp://inderal.fr/\r\nhttp://proscar.fr/\r\nhttp://zithromaxrx.fr/\r\nhttp://ciproguide.fr/\r\nhttp://doxycycline.fr/\r\nhttp://allopurinolmsnrxmsnrx.best/\r\nhttp://viagrarx.fr/\r\nhttp://arimidexmsnrxmsnrx.best/\r\n \r\n<a href=\"http://www2.airnet.ne.jp/%7Explus/bbs.cgi\">i57pyq1  u56bxw</a> 405045e","date":"2019-11-03T16:06:37.968Z"}