{"_id":"eb41a8e0-ee1a-11e9-b0ec-cd112ef33de8","name":"ugarugucolupi","email":"13e20f1f7a075e8d042d9f93ad7f0767","body":"We hkc.edxc.arapaima.uk.zgn.ga expert [URL=http://gaiaenergysystems.com/northwest-pharmacy-canada/ - pharmacy[/URL -  [URL=http://reubendangoor.com/antabuse/ - antabuse[/URL -  buy antabuse no prescription [URL=http://washingtonsharedparenting.com/xifaxan-for-sale/ - xifaxan market share[/URL -  [URL=http://disclosenews.com/cialis-professional/ - discount cialis professional[/URL -  [URL=http://addresslocality.net/tadalafil-20mg/ - cialis[/URL -  [URL=http://themusicianschoice.net/cialis-black-online/ - cialis black[/URL -  [URL=http://dallasmarketingservices.com/viagra/ - viagra[/URL -  pinnacles <a href=\"http://gaiaenergysystems.com/northwest-pharmacy-canada/\">walmart pharmacy cialis 20mg</a> <a href=\"http://reubendangoor.com/antabuse/\">antabuse foods to avoid</a> <a href=\"http://washingtonsharedparenting.com/xifaxan-for-sale/\">cheapest xifaxan</a> <a href=\"http://disclosenews.com/cialis-professional/\">cialis professional online</a> <a href=\"http://addresslocality.net/tadalafil-20mg/\">cialis</a> <a href=\"http://themusicianschoice.net/cialis-black-online/\">cialis black lowest price</a> <a href=\"http://dallasmarketingservices.com/viagra/\">viagra</a> progenitors disorders; vaccination http://gaiaenergysystems.com/northwest-pharmacy-canada/ pharmacy http://reubendangoor.com/antabuse/ list of food to avoid when taking antabuse http://washingtonsharedparenting.com/xifaxan-for-sale/ online xifaxan http://disclosenews.com/cialis-professional/ cialis professional lowest price http://addresslocality.net/tadalafil-20mg/ cialis dosage 20mg http://themusicianschoice.net/cialis-black-online/ cheap cialis black http://dallasmarketingservices.com/viagra/ discount viagra behavioral spikes.","date":"2019-10-14T00:38:20.033Z"}