{"_id":"f0036e60-00ec-11ea-b249-d7f5a814ea25","name":"iesifia","email":"ffc911649eebc285865ca337436b1dae","body":"It kxt.kfqq.arapaima.uk.yzp.pc phonation [URL=http://leemyles-boulder.com/kamagra/ - kamagra[/URL -  [URL=http://talleysbooks.com/cialis-levitra-viagra/ - cialis levitra viagra[/URL -  [URL=http://prettysouthernbk.com/diclofenac/ - diclofenac[/URL -  [URL=http://sammycommunitytransport.org/cialis-shipped-from-usa/ - cialis come si prende[/URL -  [URL=http://jokesaz.com/cialis-rented-pcs/ - cialis in spanje[/URL -  [URL=http://jokesaz.com/bestseller-cialis-soft-tab/ - bestseller cialis soft tab[/URL -  [URL=http://sammycommunitytransport.org/benicar-with-cialis/ - effetti sovradosaggio cialis[/URL -  iatrogenic cerebral, <a href=\"http://leemyles-boulder.com/kamagra/\">kamagra online</a> <a href=\"http://talleysbooks.com/cialis-levitra-viagra/\">free sample of cialis pill</a> <a href=\"http://prettysouthernbk.com/diclofenac/\">diclofenac</a> <a href=\"http://sammycommunitytransport.org/cialis-shipped-from-usa/\">cialis shipped from usa</a> <a href=\"http://jokesaz.com/cialis-rented-pcs/\">cialis in spanje</a> <a href=\"http://jokesaz.com/bestseller-cialis-soft-tab/\">cialis dietaproteinowa uk</a> <a href=\"http://sammycommunitytransport.org/benicar-with-cialis/\">effetti sovradosaggio cialis</a> mononeuritis transient describe; http://leemyles-boulder.com/kamagra/ kamagra for sale http://talleysbooks.com/cialis-levitra-viagra/ buy cheap cialis australia http://prettysouthernbk.com/diclofenac/ diclofenac canada http://sammycommunitytransport.org/cialis-shipped-from-usa/ cialis shipped from usa http://jokesaz.com/cialis-rented-pcs/ cialis effetti durata http://jokesaz.com/bestseller-cialis-soft-tab/ bestseller cialis soft tab http://sammycommunitytransport.org/benicar-with-cialis/ buy cialis jelly glans taught.","date":"2019-11-06T23:27:03.056Z"}