{"_id":"f2a6e2a0-d874-11e9-ad4c-b516289148dc","name":"emelregotaye","email":"289a2af6a7f5bf40846dd259f5db5e7d","body":"The alc.qlkc.arapaima.uk.cem.qs useless [URL=http://robots2doss.org/cialis-uk/ - generic tadalafil 20mg[/URL -  [URL=http://charlotteelliottinc.com/propecia/ - propecia[/URL -  [URL=http://hackingdiabetes.org/chloroquine/ - chloroquine[/URL -  [URL=http://ralstoncommunity.org/prednisone/ - prednisone 5mg[/URL -  [URL=http://sallyrjohnson.com/viagra/ - quick forum readtopic viagra signature content[/URL -  [URL=http://ppf-calculator.com/noroxin/ - noroxin[/URL -  speeds wards, <a href=\"http://robots2doss.org/cialis-uk/\">buy cialis with paypal</a> <a href=\"http://charlotteelliottinc.com/propecia/\">propecia generic</a> <a href=\"http://hackingdiabetes.org/chloroquine/\">cheap chloroquine</a> <a href=\"http://ralstoncommunity.org/prednisone/\">by prednisone w not prescription</a> <a href=\"http://sallyrjohnson.com/viagra/\">viagra generic</a> <a href=\"http://ppf-calculator.com/noroxin/\">noroxin lowest price</a> relied acquire http://robots2doss.org/cialis-uk/ cialis 20mg http://charlotteelliottinc.com/propecia/ propecia for sale http://hackingdiabetes.org/chloroquine/ chloroquine http://ralstoncommunity.org/prednisone/ prednisone without a prescription http://sallyrjohnson.com/viagra/ erectile dysfunction blood pressure viagra chiense viagra http://ppf-calculator.com/noroxin/ noroxin online locker constrictors ophthalmoscope.","date":"2019-09-16T11:27:21.332Z"}