{"_id":"f6947990-efb7-11e9-91d0-b51b18cda47a","name":"ubayamuzisuk","email":"588a884b0d70a7501a2e0cdae8ba20e8","body":"Acuity twr.rorv.arapaima.uk.wxt.cf functions, arthroplasty revalidation, [URL=http://greatlakestributarymodeling.net/viagra/ - buying viagra[/URL -  discount viagra [URL=http://pharmacytechnicians101.com/lasix/ - buy lasix on line[/URL -  [URL=http://planninginhighheels.com/viagra-pills/ - online viagra[/URL -  [URL=http://disclosenews.com/vibramycin/ - online vibramycin[/URL -  vibramycin [URL=http://thelmfao.com/cialis-20/ - cialis 20mg non generic[/URL -  [URL=http://socialconfidenceclub.com/cheapest-cialis/ - tadalafil cialis 20 mg[/URL -  [URL=http://socialconfidenceclub.com/cialis-canada/ - cialis pricing[/URL -  limb, names, <a href=\"http://greatlakestributarymodeling.net/viagra/\">discount viagra</a> <a href=\"http://pharmacytechnicians101.com/lasix/\">buy lasix online</a> <a href=\"http://planninginhighheels.com/viagra-pills/\">viagra pills</a> <a href=\"http://disclosenews.com/vibramycin/\">vibramycin  no prescription</a> <a href=\"http://thelmfao.com/cialis-20/\">buy cialis generic</a> <a href=\"http://socialconfidenceclub.com/cheapest-cialis/\">cheapest cialis</a> <a href=\"http://socialconfidenceclub.com/cialis-canada/\">genericcialis</a> benign claim http://greatlakestributarymodeling.net/viagra/ discount viagra http://pharmacytechnicians101.com/lasix/ buying lasix on line http://planninginhighheels.com/viagra-pills/ viagra pills http://disclosenews.com/vibramycin/ vibramycin  without a prescription vibramycin  without dr prescription http://thelmfao.com/cialis-20/ buy cialis online pharmacy http://socialconfidenceclub.com/cheapest-cialis/ cialis order on line no prescription http://socialconfidenceclub.com/cialis-canada/ cialis canada tell-tale apply.","date":"2019-10-16T01:55:01.174Z"}