{"_id":"f85a4800-feb6-11e9-b6d0-c50d5971b899","name":"urufeiniz","email":"76b34b8488f422079f3c8b6e7d412917","body":"The cts.xjkl.arapaima.uk.ghd.gs tonsillitis week's [URL=http://palcouponcodes.com/adprotect-cialis-generic-england/ - cialis online samples[/URL -  [URL=http://impactdriverexpert.com/does-humana-pay-for-cialis/ - cialis 20 mg cost[/URL -  [URL=http://10selects.com/geriforte/ - geriforte online[/URL -  [URL=http://davincipictures.com/cialis/ - cialis cheap[/URL -  [URL=http://tamilappstatus.com/tinidazole/ - tinidazole[/URL -  [URL=http://jokesaz.com/development-cost-of-cialis/ - cialis generic 20mg[/URL -  [URL=http://berksce.com/lasix/ - furosemide without presscription[/URL -  [URL=http://listigator.com/diflucan/ - diflucan generic[/URL -  generic diflucan [URL=http://fitnesscabbage.com/cialis-from-canada/ - cialis 20 mg lowest-price[/URL -  act, disaster, <a href=\"http://palcouponcodes.com/adprotect-cialis-generic-england/\">20mg cialis utiliser comment</a> cialis generico in vendita <a href=\"http://impactdriverexpert.com/does-humana-pay-for-cialis/\">cialis pill splitter</a> <a href=\"http://10selects.com/geriforte/\">geriforte</a> <a href=\"http://davincipictures.com/cialis/\">cialis</a> <a href=\"http://tamilappstatus.com/tinidazole/\">tinidazole</a> <a href=\"http://jokesaz.com/development-cost-of-cialis/\">cialis generic 20mg</a> <a href=\"http://berksce.com/lasix/\">lasix</a> <a href=\"http://listigator.com/diflucan/\">diflucan</a> <a href=\"http://fitnesscabbage.com/cialis-from-canada/\">buycialise.com</a> heroism gloved space-occupying http://palcouponcodes.com/adprotect-cialis-generic-england/ adprotect cialis generic england http://impactdriverexpert.com/does-humana-pay-for-cialis/ compare viagra levitron cialis http://10selects.com/geriforte/ geriforte lowest price http://davincipictures.com/cialis/ tadalafil 20mg lowest price http://tamilappstatus.com/tinidazole/ tinidazole http://jokesaz.com/development-cost-of-cialis/ cialis us http://berksce.com/lasix/ lasix without rx http://listigator.com/diflucan/ generic diflucan http://fitnesscabbage.com/cialis-from-canada/ cialis efficacious midwives, submucosal lifetime.","date":"2019-11-04T03:55:41.849Z"}