{"_id":"52fa0920-5f4d-11ea-b39e-95780ba77e02","name":"BarbaraAmark","email":"2f50754348f5efc59ebad2b31eb561df","body":"In my opinion it is obvious. I will not begin to speak this theme.\r\n \r\n \r\n------ \r\n<a href=http://pbprog.ru/forum/index.php?PAGE_NAME=profile_view&UID=286616>http://pbprog.ru/forum/index.php?PAGE_NAME=profile_view&UID=286616</a>\r\n \r\n \r\nЧем совершеннее техника передачи информации, тем более заурядным, пошлым, серым становится её содержание.\r\n \r\n \r\n------ \r\n<a href=https://www.avitop.com/cs/members/tororo.aspx>https://www.avitop.com/cs/members/tororo.aspx</a>\r\n \r\n \r\nЕсли тщеславие сделало кого-нибудь счастливым, то наверняка этот кто-то был дурак\r\n \r\n \r\n------ \r\n<a href=http://ntces.ru/communication/forum/user/47470/>http://ntces.ru/communication/forum/user/47470/</a>\r\n \r\n \r\nЛучше не наказывать злодеев, чем наказать невинных.\r\n \r\n \r\n------ \r\n<a href=http://rvfd.minzdravrso.ru/about/forum/user/23879/>http://rvfd.minzdravrso.ru/about/forum/user/23879/</a>\r\n \r\n \r\nБраво, вас посетила просто блестящая мысль\r\n \r\n \r\n------ \r\n<a href=http://wuz.by/forum/members/nino.21270/>http://wuz.by/forum/members/nino.21270/</a>\r\n \r\n \r\nЯ считаю, что Вы не правы. Пишите мне в PM.\r\n \r\n \r\n------ \r\n<a href=http://rdkb.minzdravrso.ru/about/forum/user/23879/>http://rdkb.minzdravrso.ru/about/forum/user/23879/</a>\r\n \r\n \r\nI think, that is not present.\r\n \r\n \r\n------ \r\n<a href=http://crbnvr.ru/about/forum/?PAGE_NAME=profile_view&UID=13678>http://crbnvr.ru/about/forum/?PAGE_NAME=profile_view&UID=13678</a>\r\n \r\n \r\nСОГЛАСЕН\r\n \r\n \r\n------ \r\n<a href=http://trackmuseum.ru/visitors/forum/user/5185/>http://trackmuseum.ru/visitors/forum/user/5185/</a>\r\n \r\n \r\nЧеловек определяется не только прирожденными качествами, но и приобретенными. .\r\n \r\n \r\n------ \r\n<a href=http://test14.info-model.ru/forum/user/40802/>http://test14.info-model.ru/forum/user/40802/</a>\r\n \r\n \r\nУзнать не трудно, а трудно привыкнуть.\r\n \r\n \r\n------ \r\n<a href=https://la-creme.ru/forum/user/3462/>https://la-creme.ru/forum/user/3462/</a>","date":"2020-03-06T01:53:50.042Z"}